{
    "typeTable": "Relational",
    "claims": {
        "0": {
            "specifications": {},
            "Measure": "Test Pos.F1",
            "Outcome": "39.0"
        },
        "1": {
            "specifications": {},
            "Measure": "Test Pos.F1",
            "Outcome": ""
        },
        "2": {
            "specifications": {},
            "Measure": "Test Pos.F1",
            "Outcome": ""
        },
        "3": {
            "specifications": {},
            "Measure": "Test Pos.F1",
            "Outcome": ""
        },
        "4": {
            "specifications": {},
            "Measure": "Test Pos.F1",
            "Outcome": ""
        },
        "5": {
            "specifications": {},
            "Measure": "Test Pos.F1",
            "Outcome": "70.7"
        },
        "6": {
            "specifications": {},
            "Measure": "Test Pos.F1",
            "Outcome": ""
        },
        "7": {
            "specifications": {},
            "Measure": "Test Pos.F1",
            "Outcome": ""
        }
    }
}